ek_ml_package/__init__.py
ek_ml_package/activation_functions.py
ek_ml_package/gaussian_discriminant_analysis.py
ek_ml_package/kmeans.py
ek_ml_package/knn.py
ek_ml_package/linear_regression.py
ek_ml_package/logistic_regression.py
ek_ml_package/loss_functions.py
ek_ml_package/neural_network.py
ek_ml_package/pca.py
ek_ml_package/perceptron.py
ek_ml_package-0.1.0.dist-info/licenses/LICENSE
ek_ml_package-0.1.0.dist-info/METADATA
ek_ml_package-0.1.0.dist-info/WHEEL
ek_ml_package-0.1.0.dist-info/top_level.txt
ek_ml_package-0.1.0.dist-info/RECORD
