Metadata-Version: 2.4
Name: ek_ml_package
Version: 0.1.0
Summary: A Python package implementing fundamental machine learning algorithms from scratch with NumPy.
Home-page: https://ekbarkacha.github.io/ek_ml_package/
Author: Emmanuel Kirui Barkacha
Author-email: ebarkacha@aimsammi.org
License: MIT
Keywords: machine learning numpy algorithms ml
Classifier: Programming Language :: Python :: 3
Classifier: License :: OSI Approved :: MIT License
Classifier: Operating System :: OS Independent
Classifier: Topic :: Scientific/Engineering :: Artificial Intelligence
Requires-Python: >=3.6
License-File: LICENSE
Requires-Dist: numpy
Requires-Dist: matplotlib
Dynamic: author
Dynamic: author-email
Dynamic: classifier
Dynamic: description
Dynamic: description-content-type
Dynamic: home-page
Dynamic: keywords
Dynamic: license
Dynamic: license-file
Dynamic: requires-dist
Dynamic: requires-python
Dynamic: summary
